README.rst
setup.cfg
setup.py
EAST.egg-info/PKG-INFO
EAST.egg-info/SOURCES.txt
EAST.egg-info/dependency_links.txt
EAST.egg-info/entry_points.txt
EAST.egg-info/requires.txt
EAST.egg-info/top_level.txt
analysis/__init__.py
analysis/memory.py
analysis/runtime.py
analysis/synonyms.py
analysis/utils.py
east/__init__.py
east/applications.py
east/consts.py
east/exceptions.py
east/formatting.py
east/main.py
east/utils.py
east/asts/__init__.py
east/asts/ast.py
east/asts/ast_linear.py
east/asts/ast_naive.py
east/asts/base.py
east/asts/easa.py
east/asts/utils.py
east/synonyms/__init__.py
east/synonyms/synonyms.py
east/synonyms/utils.py
tests/__init__.py
tests/test_utils.py
tests/asts/__init__.py
tests/asts/test_base.py
tests/asts/test_utils.py