Metadata-Version: 1.1
Name: EAST
Version: 0.3.5
Summary: Text analysis library based on the Annotated Suffix Tree method
Home-page: https://github.com/msdubov/AST-text-analysis
Author: Mikhail Dubov
Author-email: msdubov@gmail.com
License: MIT
Download-URL: https://github.com/msdubov/AST-text-analysis/tarball/0.3.5
Keywords: text analysis,suffix tree,synonym extraction
Platform: UNKNOWN
